setup.py
googleplay_api/__init__.py
googleplay_api/googleplay.py
googleplay_api/googleplay_pb2.py
googleplay_api.egg-info/PKG-INFO
googleplay_api.egg-info/SOURCES.txt
googleplay_api.egg-info/dependency_links.txt
googleplay_api.egg-info/requires.txt
googleplay_api.egg-info/top_level.txt