Metadata-Version: 1.1
Name: googleplay-api
Version: 0.1.0
Summary: An unofficial Python API that let you search, browse and download Android apps from Google Play (formerly Android Market).
Home-page: https://github.com/NeroBurner/googleplay-api
Author: NeroBurner
Author-email: pyro4hell@gmail.com
License: BSD
Keywords: GooglePlayStore apk
Platform: UNKNOWN
Classifier: Development Status :: 3 - Alpha
Classifier: Intended Audience :: Developers
Classifier: Topic :: Software Development :: Build Tools
Classifier: License :: OSI Approved :: BSD License
Classifier: Programming Language :: Python :: 2
Classifier: Programming Language :: Python :: 2.7
Classifier: Programming Language :: Python :: 3
Classifier: Programming Language :: Python :: 3.4
